flowmeter/__init__.py
flowmeter/flowmeter.py
flowmeter/flowsession.py
prc_flowmeter-0.2.4.dist-info/LICENSE
prc_flowmeter-0.2.4.dist-info/METADATA
prc_flowmeter-0.2.4.dist-info/WHEEL
prc_flowmeter-0.2.4.dist-info/top_level.txt
prc_flowmeter-0.2.4.dist-info/RECORD
