Metadata-Version: 2.1
Name: prc-flowmeter
Version: 0.2.4
Summary: A tool for deriving statistical features from pcap data.
Home-page: https://github.com/prc-hsv/flowmeter
Author: Stephen Wight
Author-email: swight@prc-hsv.com
License: UNKNOWN
Platform: UNKNOWN
Classifier: Programming Language :: Python :: 3
Classifier: Operating System :: OS Independent
Requires-Python: >=3.6
License-File: LICENSE
Requires-Dist: numpy
Requires-Dist: pandas
Requires-Dist: scapy
Requires-Dist: lockfile
Requires-Dist: joblib
